latexgen/__init__.py
latexgen/image.py
latexgen/table.py
latexgen_zakr600-0.1.0.dist-info/METADATA
latexgen_zakr600-0.1.0.dist-info/WHEEL
latexgen_zakr600-0.1.0.dist-info/top_level.txt
latexgen_zakr600-0.1.0.dist-info/RECORD
