Metadata-Version: 2.4
Name: latexgen-zakr600
Version: 0.1.0
Summary: Functional LaTeX generator
Author: Zakhar Kravchuk
Requires-Python: >=3.8
